<?xml version="1.0" encoding="UTF-8"?>
<!DOCTYPE mapper PUBLIC "-//mybatis.org//DTD Mapper 3.0//EN" "http://mybatis.org/dtd/mybatis-3-mapper.dtd">
<mapper namespace="com.dao.EcsEcsmartArticleCatMapper">
  <resultMap id="BaseResultMap" type="com.entity.EcsEcsmartArticleCat">
    <!--
      WARNING - @mbg.generated
      This element is automatically generated by MyBatis Generator, do not modify.
    -->
    <id column="cat_id" jdbcType="SMALLINT" property="cat_id" />
    <result column="cat_name" jdbcType="VARCHAR" property="cat_name" />
    <result column="cat_type" jdbcType="BIT" property="cat_type" />
    <result column="keywords" jdbcType="VARCHAR" property="keywords" />
    <result column="cat_desc" jdbcType="VARCHAR" property="cat_desc" />
    <result column="sort_order" jdbcType="TINYINT" property="sort_order" />
    <result column="show_in_nav" jdbcType="BIT" property="show_in_nav" />
    <result column="parent_id" jdbcType="SMALLINT" property="parent_id" />
  </resultMap>
  <delete id="deleteByPrimaryKey" parameterType="java.lang.Short">
    <!--
      WARNING - @mbg.generated
      This element is automatically generated by MyBatis Generator, do not modify.
    -->
    delete from ecs_ecsmart_article_cat
    where cat_id = #{cat_id,jdbcType=SMALLINT}
  </delete>
  <insert id="insert" parameterType="com.entity.EcsEcsmartArticleCat">
    <!--
      WARNING - @mbg.generated
      This element is automatically generated by MyBatis Generator, do not modify.
    -->
    insert into ecs_ecsmart_article_cat (cat_id, cat_name, cat_type, 
      keywords, cat_desc, sort_order, 
      show_in_nav, parent_id)
    values (#{cat_id,jdbcType=SMALLINT}, #{cat_name,jdbcType=VARCHAR}, #{cat_type,jdbcType=BIT}, 
      #{keywords,jdbcType=VARCHAR}, #{cat_desc,jdbcType=VARCHAR}, #{sort_order,jdbcType=TINYINT}, 
      #{show_in_nav,jdbcType=BIT}, #{parent_id,jdbcType=SMALLINT})
  </insert>
  <update id="updateByPrimaryKey" parameterType="com.entity.EcsEcsmartArticleCat">
    <!--
      WARNING - @mbg.generated
      This element is automatically generated by MyBatis Generator, do not modify.
    -->
    update ecs_ecsmart_article_cat
    set cat_name = #{cat_name,jdbcType=VARCHAR},
      cat_type = #{cat_type,jdbcType=BIT},
      keywords = #{keywords,jdbcType=VARCHAR},
      cat_desc = #{cat_desc,jdbcType=VARCHAR},
      sort_order = #{sort_order,jdbcType=TINYINT},
      show_in_nav = #{show_in_nav,jdbcType=BIT},
      parent_id = #{parent_id,jdbcType=SMALLINT}
    where cat_id = #{cat_id,jdbcType=SMALLINT}
  </update>
  <select id="selectByPrimaryKey" parameterType="java.lang.Short" resultMap="BaseResultMap">
    <!--
      WARNING - @mbg.generated
      This element is automatically generated by MyBatis Generator, do not modify.
    -->
    select cat_id, cat_name, cat_type, keywords, cat_desc, sort_order, show_in_nav, parent_id
    from ecs_ecsmart_article_cat
    where cat_id = #{cat_id,jdbcType=SMALLINT}
  </select>
  <select id="selectAll" resultMap="BaseResultMap">
    <!--
      WARNING - @mbg.generated
      This element is automatically generated by MyBatis Generator, do not modify.
    -->
    select cat_id, cat_name, cat_type, keywords, cat_desc, sort_order, show_in_nav, parent_id
    from ecs_ecsmart_article_cat
  </select>
</mapper>